afinn/__init__.py
afinn/afinn.py
afinn/data/AFINN-111.txt
afinn/data/AFINN-96.txt
afinn/data/AFINN-da-32.txt
afinn/data/AFINN-emoticon-8.txt
afinn/data/AFINN-en-165-gaming.txt
afinn/data/AFINN-en-165.txt
afinn/data/AFINN-fr-165.txt
afinn/data/AFINN-sv-165.txt
afinn_gaming-0.1.dev0.dist-info/LICENSE
afinn_gaming-0.1.dev0.dist-info/METADATA
afinn_gaming-0.1.dev0.dist-info/WHEEL
afinn_gaming-0.1.dev0.dist-info/top_level.txt
afinn_gaming-0.1.dev0.dist-info/RECORD
