Metadata-Version: 2.1
Name: afinn-gaming
Version: 0.1.dev0
Summary: AFINN sentiment analysis for gaming
Home-page: https://github.com/korsmed/afinn
Author: Lukas Corona
Author-email: luk.corona@gmail.com
License: Apache License 2.0
Keywords: sentiment analysis
Platform: UNKNOWN
Classifier: Programming Language :: Python :: 2.6
Classifier: Programming Language :: Python :: 2.7
Classifier: Programming Language :: Python :: 3.3
Classifier: Programming Language :: Python :: 3.4
Classifier: Programming Language :: Python :: 3.5
